EwanSonicConnector/__init__.py
EwanSonicConnector/connect_to_sonic.py
EwanSonicConnector/cos_store.py
tests/__init__.py
tests/hello.py
EwanSonicConnector-0.1.26.dist-info/LICENSE
EwanSonicConnector-0.1.26.dist-info/METADATA
EwanSonicConnector-0.1.26.dist-info/WHEEL
EwanSonicConnector-0.1.26.dist-info/top_level.txt
EwanSonicConnector-0.1.26.dist-info/RECORD
