Metadata-Version: 2.1
Name: EwanSonicConnector
Version: 0.1.26
Summary: 给ewan内部使用的一个连接云真机sonic的连接器
Author: fulage
Author-email: fulage@ewan.cn
Classifier: Development Status :: 3 - Alpha
Classifier: Programming Language :: Python :: 3
Classifier: License :: OSI Approved :: MIT License
Requires-Python: >=3.6
License-File: LICENSE
Requires-Dist: redis>=4.5.4
Requires-Dist: requests>=2.31.0
Requires-Dist: airtest>=1.3.5
Requires-Dist: cos-python-sdk-v5>=1.9.33
